[
  {
    "id": 1,
    "titles": "এসএমই",
    "headings": "ভোনোম এসএমই পেমেন্ট",
    "subHeadings": "বিক্রয় পেশাদার এবং গ্রাহকদের দলের জন্য",
    "contents": "দলের সহযোগিতা এবং উৎসাহন উন্নত করতে টাস্ক এবং কার্যপ্রবাহ পরিচালনা করুন।",
    "options":[
      {
        "content": "1দলের সহযোগিতা এবং উৎপাদনশীলতা বৃদ্ধি করতে টাস্ক এবং কার্যপ্রবাহ পরিচালনা করুন।"
      },
      {
        "content": "2দলের সহযোগিতা এবং উৎপাদনশীলতা বৃদ্ধি করতে টাস্ক এবং কার্যপ্রবাহ পরিচালনা করুন।"
      },
      {
        "content": "3দলের সহযোগিতা এবং উৎপাদনশীলতা বৃদ্ধি করতে টাস্ক এবং কার্যপ্রবাহ পরিচালনা করুন।"
      }
    ]
  },
  {
    "id": 2,
    "titles": "ইআরপি",
    "headings": "ভোনোম ইআরপি পেমেন্ট",
    "subHeadings": "বিক্রয় পেশাদার এবং গ্রাহকদের দলের জন্য",
    "contents": "দলের সহযোগিতা এবং উৎসাহন উন্নত করতে টাস্ক এবং কার্যপ্রবাহ পরিচালনা করুন।",
    "options":[
      {
        "content": "1দলের সহযোগিতা এবং উৎপাদনশীলতা বৃদ্ধি করতে টাস্ক এবং কার্যপ্রবাহ পরিচালনা করুন।"
      },
      {
        "content": "2দলের সহযোগিতা এবং উৎপাদনশীলতা বৃদ্ধি করতে টাস্ক এবং কার্যপ্রবাহ পরিচালনা করুন।"
      },
      {
        "content": "3দলের সহযোগিতা এবং উৎপাদনশীলতা বৃদ্ধি করতে টাস্ক এবং কার্যপ্রবাহ পরিচালনা করুন।"
      }
    ]
  },
  {
    "id": 3,
    "titles": "সিআরএম",
    "headings": "ভোনোম সিআরএম পেমেন্ট",
    "subHeadings": "বিক্রয় পেশাদার এবং গ্রাহকদের দলের জন্য",
    "contents": "দলের সহযোগিতা এবং উৎসাহন উন্নত করতে টাস্ক এবং কার্যপ্রবাহ পরিচালনা করুন।",
    "options":[
      {
        "content": "1দলের সহযোগিতা এবং উৎপাদনশীলতা বৃদ্ধি করতে টাস্ক এবং কার্যপ্রবাহ পরিচালনা করুন।"
      },
      {
        "content": "2দলের সহযোগিতা এবং উৎপাদনশীলতা বৃদ্ধি করতে টাস্ক এবং কার্যপ্রবাহ পরিচালনা করুন।"
      },
      {
        "content": "3দলের সহযোগিতা এবং উৎপাদনশীলতা বৃদ্ধি করতে টাস্ক এবং কার্যপ্রবাহ পরিচালনা করুন।"
      }
    ]
  },
  {
    "id": 4,
    "titles": "এইচআর",
    "headings": "ভোনোম এইচআর পেমেন্ট",
    "subHeadings": "বিক্রয় পেশাদার এবং গ্রাহকদের দলের জন্য",
    "contents": "দলের সহযোগিতা এবং উৎসাহন উন্নত করতে টাস্ক এবং কার্যপ্রবাহ পরিচালনা করুন।",
    "options":[
      {
        "content": "1দলের সহযোগিতা এবং উৎপাদনশীলতা বৃদ্ধি করতে টাস্ক এবং কার্যপ্রবাহ পরিচালনা করুন।"
      },
      {
        "content": "2দলের সহযোগিতা এবং উৎপাদনশীলতা বৃদ্ধি করতে টাস্ক এবং কার্যপ্রবাহ পরিচালনা করুন।"
      },
      {
        "content": "3দলের সহযোগিতা এবং উৎপাদনশীলতা বৃদ্ধি করতে টাস্ক এবং কার্যপ্রবাহ পরিচালনা করুন।"
      }
    ]
  },
  {
    "id": 5,
    "titles": "ইনভয়েস",
    "headings": "ভোনোম ইনভয়েস পেমেন্ট",
    "subHeadings": "বিক্রয় পেশাদার এবং গ্রাহকদের দলের জন্য",
    "contents": "দলের সহযোগিতা এবং উৎসাহন উন্নত করতে টাস্ক এবং কার্যপ্রবাহ পরিচালনা করুন।",
    "options":[
      {
        "content": "1দলের সহযোগিতা এবং উৎপাদনশীলতা বৃদ্ধি করতে টাস্ক এবং কার্যপ্রবাহ পরিচালনা করুন।"
      },
      {
        "content": "2দলের সহযোগিতা এবং উৎপাদনশীলতা বৃদ্ধি করতে টাস্ক এবং কার্যপ্রবাহ পরিচালনা করুন।"
      },
      {
        "content": "3দলের সহযোগিতা এবং উৎপাদনশীলতা বৃদ্ধি করতে টাস্ক এবং কার্যপ্রবাহ পরিচালনা করুন।"
      }
    ]

  },
  {
    "id": 6,
    "titles": "অ্যাকাউন্টিং",
    "headings": "ভোনোম অ্যাকাউন্টিং পেমেন্ট",
    "subHeadings": "বিক্রয় পেশাদার এবং গ্রাহকদের দলের জন্য",
    "contents": "দলের সহযোগিতা এবং উৎসাহন উন্নত করতে টাস্ক এবং কার্যপ্রবাহ পরিচালনা করুন।",
    "options":[
      {
        "content": "1দলের সহযোগিতা এবং উৎপাদনশীলতা বৃদ্ধি করতে টাস্ক এবং কার্যপ্রবাহ পরিচালনা করুন।"
      },
      {
        "content": "2দলের সহযোগিতা এবং উৎপাদনশীলতা বৃদ্ধি করতে টাস্ক এবং কার্যপ্রবাহ পরিচালনা করুন।"
      },
      {
        "content": "3দলের সহযোগিতা এবং উৎপাদনশীলতা বৃদ্ধি করতে টাস্ক এবং কার্যপ্রবাহ পরিচালনা করুন।"
      }
    ]
  },
  {
    "id": 7,
    "titles": "টাস্ক বিং",
    "headings": "ভোনোম টাস্ক বিং",
    "subHeadings": "বিক্রয় পেশাদার এবং গ্রাহকদের দলের জন্য",
    "contents": "দলের সহযোগিতা এবং উৎসাহন উন্নত করতে টাস্ক এবং কার্যপ্রবাহ পরিচালনা করুন।",
    "options":[
      {
        "content": "1দলের সহযোগিতা এবং উৎপাদনশীলতা বৃদ্ধি করতে টাস্ক এবং কার্যপ্রবাহ পরিচালনা করুন।"
      },
      {
        "content": "2দলের সহযোগিতা এবং উৎপাদনশীলতা বৃদ্ধি করতে টাস্ক এবং কার্যপ্রবাহ পরিচালনা করুন।"
      },
      {
        "content": "3দলের সহযোগিতা এবং উৎপাদনশীলতা বৃদ্ধি করতে টাস্ক এবং কার্যপ্রবাহ পরিচালনা করুন।"
      }
    ]
  }
]
