[
  {
    "id": 1,
    "image": "assets/crm-content.png",
    "headings":"দক্ষ কাজ সংগঠন",
    "subHeading": "<span style='color: #0079FF'>সংকুচিত কাজ ট্র্যাকিং</span>",
    "description": "কাজগুলি দক্ষভাবে সংগঠন করুন, প্রাথমিকতা নির্ধারণ করুন, নির্ধারিত তারিখ সেট করুন, এবং অগ্রগতি ট্র্যাক করুন যাতে উত্পাদকতা উন্নত করতে এবং প্রকল্পগুলি সময়ের মধ্যে সম্পন্ন হয়।",
    "AccordianHeading":"সহযোগিতামূলক কাজস্থল",
    "AccordianContents": "দলের জন্য যৌথ কাজস্থল তৈরি করুন, সমন্বিত সহযোগিতা, যোগাযোগ এবং কাজের সমন্বয় সহজলভ্য করুন, দলের কাজের সমন্বয় এবং উন্নত উত্পাদকতা উন্নত করতে।",
    "expanded": false
  },
  {
    "id": 2,
    "image": "assets/crm-content2.png",
    "headings":"স্মরণ এবং বিজ্ঞপ্তি",
    "subHeading":"<span style='color: #00DFA2;'>সময়ে কাজের স্মরণ</span>",
    "description":"আসন্ন কাজের জন্য স্মরণ এবং বিজ্ঞপ্তি পেয়ে গুরুত্বপূর্ণ শেষতারিখগুলি না হারিয়ে এবং কাজগুলি সম্পূর্ণ হয়ে যায় সময়ে। শীর্ষে থাকুন শেষতারিখের উপর।",
    "AccordianHeading":"কাজ দায়িত্ব নির্ধারণ এবং ধারাবাহিক করুন",
    "AccordianContents":"দলের সদস্যদেরকে কাজ দায়িত্বশীল করুন, দায়িত্ব ব deleg করুন, এবং অগ্রগতি ট্র্যাক করুন, দায়িত্বশীলতা উন্নত করবে এবং কাজগুলি উচিতভাবে বিতরণ করবে।",
    "expanded": false
  },
  {
    "id": 3,
    "image": "assets/crm-content1.png",
    "headings":"কাজ ট্র্যাকিং এবং বিশ্লেষণ",
    "subHeading":"<span style='color:#FF0060;'>ডেটা সম্মিলিত কর্মক্ষমতা মূল্যায়ন</span>",
    "description":"কাজের অগ্রগতি মনিটর করুন, সম্পূর্ণন হার ট্র্যাক করুন, এবং বিশ্লেষণের মাধ্যমে অধিগম করুন, কর্মক্ষমতা এবং উন্নতির জন্য ডেটা-নির্দিষ্ট মূল্যায়ন সক্ষম করা এবং উন্নতির জন্য ক্ষেত্রগুলি সনাক্ত করা।",
    "AccordianHeading":"সংমিলন এবং স্বয়ংক্রিয়করণ",
    "AccordianContents":"অন্যান্য সরঞ্জাম এবং সিস্টেমগুলির সাথে কাজ বিং সংমিলন করুন, পুনরাবৃত্ত কাজগুলি স্বয়ংক্রিয়ভাবে করুন, এবং কর্মপ্রবাহ সমন্বয় করুন, দক্ষতা উন্নত করুন এবং ম্যানুয়াল প্রয়াস কমান।",
    "expanded": false
  }
]
