[
  {
    "url": "assets/dynamic/Vector (2).svg",
    "headings": "সর্বদা সাম্প্রতিক প্রযুক্তি",
    "contents": "সর্বদা সাম্প্রতিক প্রযুক্তির উন্নতিগতি এবং আবিষ্কারে অবিচ্ছিন্ন থাকুন। আমাদের উচ্চমানের সমাধান সরবরাহ করার আদর্শ নিশ্চিত করে যে আপনি সর্বদা প্রযুক্তির সারিস্টারে অগ্রসর থাকেন।"
  },
  {
    "url": "assets/dynamic/Vector (3).svg",
    "headings": "সাইবার এবং ডেটা নিরাপত্তা",
    "contents": "আমাদের ব্যাপক সাইবার এবং ডেটা নিরাপত্তা সমাধান নিশ্চিত করে যে আপনার মৌলিক তথ্য নিরাপত্তামূলক এবং নিরাপদ থাকে। আমাদের নতুনতম নিরাপত্তা মেয়াদসমূহ দিয়ে আপনার ডিজিটাল সম্পদ সুরক্ষিত করুন।"
  },
  {
    "url": "assets/dynamic/Vector (4).svg",
    "headings": "আধুনিক ডিজাইন এবং অভিজ্ঞতা",
    "contents": "আমাদের আধুনিক এবং অবজ্ঞানমূলক ডিজাইনগুলির সাথে একটি অসাধারণ ডিজিটাল অভিজ্ঞতায় ডুবে যান। আমরা ব্যবহারকারী-মন্দিরিত ইন্টারফেস তৈরি করি যা সৌন্দর্য ও কার্যক্ষমতা দুটি সমন্বয় করে।"
  },
  {
    "url": "assets/dynamic/Vector (5).svg",
    "headings": "বহুভাষিক সাপোর্ট",
    "contents": "আমাদের বহুভাষিক সাপোর্ট দিয়ে আপনি আপনার প্রাপ্তিসাধন প্রসার করুন। আপনার বৈশ্বিক পাঠকবৃন্দ সাথে দ্বীপবর্ধন করুন এবং তাদের পছন্দের ভাষায় একটি সহজলভ্য অভিজ্ঞতা সরবরাহ করুন।"
  },
  {
    "url": "assets/dynamic/Vector (6).svg",
    "headings": "অসীম কাস্টমাইজেশন",
    "contents": "আপনি যেভাবে চিত্রণ করেন তা অনুসারে আপনার ডিজিটাল উপস্থিতি সাজান। অসীম কাস্টমাইজেশন বিকল্পগুলি দিয়ে, আপনি একটি অনন্য এবং ব্যক্তিগত অনলাইন প্ল্যাটফর্ম তৈরি করতে পারেন।"
  },
  {
    "url": "assets/dynamic/Vector (7).svg",
    "headings": "কাস্টম ফর্ম এবং রিপোর্ট ডিজাইন",
    "contents": "আমাদের কাস্টম ফর্ম এবং রিপোর্ট ডিজাইন দিয়ে দক্ষভাবে ডেটা সংগ্রহ করুন এবং বিষয় বুদ্ধিমত্তা অর্জন করুন। আরও ভাল সিদ্ধান্ত নেওয়ার জন্য আপনার ডেটা প্রবন্ধন প্রক্রিয়াগুলি সরলীকৃত করুন।"
  },
  {
    "url": "assets/dynamic/Vector (8).svg",
    "headings": "রিয়েল-টাইম ইন্টিগ্রেশন এবং অটোমেশন",
    "contents": "আমাদের সহজ ইন্টিগ্রেশন এবং অটোমেশন সমাধানগুলি দিয়ে প্রক্রিয়াগুলি সত্যিকারে সময়ে সংযুক্ত করুন এবং স্বয়ংক্রিয়করণ করুন। দক্ষতা উন্নত করুন এবং ম্যানুয়াল শ্রমজনিত কাজের লোড কমান।"
  },
  {
    "url": "assets/dynamic/Vector (9).svg",
    "headings": "কাস্টমাইজয়েবল ড্যাশবোর্ড",
    "contents": "আমাদের কাস্টমাইজয়েবল ড্যাশবোর্ড দিয়ে এক নজরে গুরুত্বপূর্ণ উপলব্ধিগুলি এবং ডেটা অ্যাক্সেস করুন। আপনির জন্য সবচেয়ে গুরুত্বপূর্ণ তথ্য প্রদর্শন করার জন্য আপনার ড্যাশবোর্ড কাস্টমাইজ করুন।"
  },
  {
    "url": "assets/dynamic/Vector (10).svg",
    "headings": "রিয়েল-টাইমে লাইভ চ্যাট, লক্ষ্যগুলি, সহযোগিতা",
    "contents": "রিয়েল-টাইমে লাইভ চ্যাট দ্বারা আপনার পাঠকবৃন্দে একত্রিত হোন, আপনার লক্ষ্যগুলি ট্র্যাক করুন এবং সহযোগিতামূলকভাবে সহযোগিতা করুন সত্যিকারে সময়ে। উত্তরণ বেশি যোগাযোগ এবং দক্ষতা উন্নত করুন।"
  }
]
